derpibooru/__init__.py
derpibooru/comment.py
derpibooru/helpers.py
derpibooru/image.py
derpibooru/query.py
derpibooru/request.py
derpibooru/search.py
derpibooru/sort.py
derpibooru/user.py
tests/__init__.py
tests/test_random_parameters.py
tests/test_search_live.py
DerPyBooru-0.7.5.dist-info/LICENSE.txt
DerPyBooru-0.7.5.dist-info/METADATA
DerPyBooru-0.7.5.dist-info/WHEEL
DerPyBooru-0.7.5.dist-info/top_level.txt
DerPyBooru-0.7.5.dist-info/RECORD
