Metadata-Version: 2.1
Name: DerPyBooru
Version: 0.7.5
Summary: Python bindings for Derpibooru's API
Home-page: https://github.com/joshua-stone/DerPyBooru
Author: Joshua Stone
Author-email: joshua.gage.stone@gmail.com
License: Simplified BSD License
Download-URL: https://github.com/joshua-stone/DerPyBooru/tarball/0.7.2
Platform: any
Classifier: Development Status :: 4 - Beta
Classifier: Intended Audience :: Developers
Classifier: Operating System :: OS Independent
Classifier: License :: OSI Approved :: BSD License
Classifier: Topic :: Software Development :: Libraries :: Python Modules
Classifier: Programming Language :: Python :: 2.7
Classifier: Programming Language :: Python :: 3
Requires-Dist: requests
